<?xml version="1.0" encoding="UTF-8"?>
<objects serializationModel="Studio.02.02.00">
	<object class="AudioFile" id="{97e747f2-e2fb-4bc0-a061-4587b5c0190e}">
		<property name="assetPath">
			<value>Footsteps - Essentials/Footsteps_Gravel/Footsteps_Gravel_Run/Footsteps_Gravel_Run_07.wav</value>
		</property>
		<property name="frequencyInKHz">
			<value>48</value>
		</property>
		<property name="channelCount">
			<value>1</value>
		</property>
		<property name="length">
			<value>0.38610416666666669</value>
		</property>
		<relationship name="masterAssetFolder">
			<destination>{1e2c1ada-94e6-4be3-8832-9d6b22150cb0}</destination>
		</relationship>
	</object>
</objects>
